{
  "version": 1,
  "inputs": {
    "year": "2024",
    "revenue": "11552.62",
    "coeff": "0.67",
    "taxRate": "0.05",
    "inpsType": "gestione_separata",
    "inpsRate": "0.26",
    "inpsDeductible": true,
    "applyAcconti": true,
    "splitModel": "standard",
    "customSplitJune": "0.4",
    "customSplitNovember": "0.6"
  },
  "defaults": {
    "year": "2024",
    "revenue": "11552.62",
    "coeff": "0.67",
    "taxRate": "0.05",
    "inpsType": "gestione_separata",
    "inpsRate": "0.26",
    "inpsDeductible": true,
    "applyAcconti": true,
    "splitModel": "standard",
    "customSplitJune": "0.4",
    "customSplitNovember": "0.6"
  }
}
